README.txt
setup.py
troll/__init__.py
troll.storage.egg-info/PKG-INFO
troll.storage.egg-info/SOURCES.txt
troll.storage.egg-info/dependency_links.txt
troll.storage.egg-info/namespace_packages.txt
troll.storage.egg-info/requires.txt
troll.storage.egg-info/top_level.txt
troll.storage.egg-info/zip-safe
troll/storage/__init__.py
troll/storage/base.py
troll/storage/container.py
troll/storage/descriptors.py
troll/storage/interfaces.py
troll/storage/tests/__init__.py
troll/storage/tests/annotation.py
troll/storage/tests/configure.zcml
troll/storage/tests/test_all.py