Metadata-Version: 1.0
Name: troll.storage
Version: 0.4
Summary: Troll abstract storage layer
Home-page: http://tracker.trollfot.org/
Author: Souheil Chelfouh
Author-email: souheil@chelfouh.com
License: GPL
Download-URL: http://pypi.python.org/pypi/troll.storage
Keywords: zope grok storage
Platform: Any
Classifier: Development Status :: 5 - Production/Stable
Classifier: Environment :: Web Environment
Classifier: Framework :: Zope
Classifier: Intended Audience :: Developers
Classifier: License :: OSI Approved :: GNU General Public License (GPL)
Classifier: Operating System :: OS Independent
Classifier: Programming Language :: Python
Classifier: Topic :: Software Development :: Libraries :: Python Modules
